{
  "item": [
    {
      "id": "f6c780e7-67cd-40f4-8a87-ba3d0629f187",
      "name": "Countries",
      "description": {
        "content": "",
        "type": "text/plain"
      },
      "item": [
        {
          "id": "7f73dae1-e653-4d49-a536-9fb0ac562052",
          "name": "List Countries",
          "request": {
            "name": "List Countries",
            "description": {
              "content": "Get all countries with their names, slugs, and alpha-2 codes.",
              "type": "text/plain"
            },
            "url": {
              "path": [
                "countries"
              ],
              "host": [
                "{{baseUrl}}"
              ],
              "query": [],
              "variable": []
            },
            "header": [
              {
                "key": "Accept",
                "value": "application/json"
              }
            ],
            "method": "GET",
            "auth": null
          },
          "response": [
            {
              "id": "14f4fcc2-17ec-4862-9751-5593fa6ebeb2",
              "name": "List of countries",
              "originalRequest": {
                "url": {
                  "path": [
                    "countries"
                  ],
                  "host": [
                    "{{baseUrl}}"
                  ],
                  "query": [],
                  "variable": []
                },
                "header": [
                  {
                    "description": {
                      "content": "Added as a part of security scheme: apikey",
                      "type": "text/plain"
                    },
                    "key": "X-API-Key",
                    "value": "<API Key>"
                  },
                  {
                    "key": "Accept",
                    "value": "application/json"
                  }
                ],
                "method": "GET",
                "body": {}
              },
              "status": "OK",
              "code": 200,
              "header": [
                {
                  "key": "Content-Type",
                  "value": "application/json"
                }
              ],
              "body": "{\n  \"countries\": [\n    {\n      \"name\": \"string\",\n      \"slug\": \"string\",\n      \"code\": \"string\",\n      \"continent\": \"string\"\n    },\n    {\n      \"name\": \"string\",\n      \"slug\": \"string\",\n      \"code\": \"string\",\n      \"continent\": \"string\"\n    }\n  ],\n  \"count\": 2487\n}",
              "cookie": [],
              "_postman_previewlanguage": "json"
            },
            {
              "id": "7be4d442-174c-477a-8383-019cb9f7b394",
              "name": "Invalid or missing API key",
              "originalRequest": {
                "url": {
                  "path": [
                    "countries"
                  ],
                  "host": [
                    "{{baseUrl}}"
                  ],
                  "query": [],
                  "variable": []
                },
                "header": [
                  {
                    "description": {
                      "content": "Added as a part of security scheme: apikey",
                      "type": "text/plain"
                    },
                    "key": "X-API-Key",
                    "value": "<API Key>"
                  },
                  {
                    "key": "Accept",
                    "value": "application/json"
                  }
                ],
                "method": "GET",
                "body": {}
              },
              "status": "Unauthorized",
              "code": 401,
              "header": [
                {
                  "key": "Content-Type",
                  "value": "application/json"
                }
              ],
              "body": "{\n  \"error\": \"string\",\n  \"message\": \"string\",\n  \"statusCode\": 9675\n}",
              "cookie": [],
              "_postman_previewlanguage": "json"
            }
          ],
          "event": [],
          "protocolProfileBehavior": {
            "disableBodyPruning": true
          }
        },
        {
          "id": "306232df-5311-4278-aed7-35c88365c63f",
          "name": "Get Country",
          "request": {
            "name": "Get Country",
            "description": {
              "content": "Get detailed information for a specific country by slug or alpha-2 code.",
              "type": "text/plain"
            },
            "url": {
              "path": [
                "countries",
                ":id"
              ],
              "host": [
                "{{baseUrl}}"
              ],
              "query": [],
              "variable": [
                {
                  "disabled": false,
                  "type": "any",
                  "value": "<string>",
                  "key": "id",
                  "description": "(Required) Country slug or alpha-2 code (e.g., \"france\" or \"FR\")"
                }
              ]
            },
            "header": [
              {
                "key": "Accept",
                "value": "application/json"
              }
            ],
            "method": "GET",
            "auth": null
          },
          "response": [
            {
              "id": "5fd866ca-9a3d-4fb0-96d6-4567211d2712",
              "name": "Country details",
              "originalRequest": {
                "url": {
                  "path": [
                    "countries",
                    ":id"
                  ],
                  "host": [
                    "{{baseUrl}}"
                  ],
                  "query": [],
                  "variable": [
                    {
                      "disabled": false,
                      "type": "any",
                      "value": "<string>",
                      "key": "id",
                      "description": "(Required) Country slug or alpha-2 code (e.g., \"france\" or \"FR\")"
                    }
                  ]
                },
                "header": [
                  {
                    "description": {
                      "content": "Added as a part of security scheme: apikey",
                      "type": "text/plain"
                    },
                    "key": "X-API-Key",
                    "value": "<API Key>"
                  },
                  {
                    "key": "Accept",
                    "value": "application/json"
                  }
                ],
                "method": "GET",
                "body": {}
              },
              "status": "OK",
              "code": 200,
              "header": [
                {
                  "key": "Content-Type",
                  "value": "application/json"
                }
              ],
              "body": "{\n  \"name\": \"string\",\n  \"slug\": \"string\",\n  \"code\": \"string\",\n  \"continent\": \"string\",\n  \"capital\": \"string\",\n  \"currency\": \"string\",\n  \"languages\": [\n    \"string\",\n    \"string\"\n  ],\n  \"population\": 9842,\n  \"timezone\": \"string\",\n  \"callingCode\": \"string\"\n}",
              "cookie": [],
              "_postman_previewlanguage": "json"
            },
            {
              "id": "ba946988-3cfc-4210-9445-4fe06ac06ccf",
              "name": "Resource not found",
              "originalRequest": {
                "url": {
                  "path": [
                    "countries",
                    ":id"
                  ],
                  "host": [
                    "{{baseUrl}}"
                  ],
                  "query": [],
                  "variable": [
                    {
                      "disabled": false,
                      "type": "any",
                      "value": "<string>",
                      "key": "id",
                      "description": "(Required) Country slug or alpha-2 code (e.g., \"france\" or \"FR\")"
                    }
                  ]
                },
                "header": [
                  {
                    "description": {
                      "content": "Added as a part of security scheme: apikey",
                      "type": "text/plain"
                    },
                    "key": "X-API-Key",
                    "value": "<API Key>"
                  },
                  {
                    "key": "Accept",
                    "value": "application/json"
                  }
                ],
                "method": "GET",
                "body": {}
              },
              "status": "Not Found",
              "code": 404,
              "header": [
                {
                  "key": "Content-Type",
                  "value": "application/json"
                }
              ],
              "body": "{\n  \"error\": \"string\",\n  \"message\": \"string\",\n  \"statusCode\": 9675\n}",
              "cookie": [],
              "_postman_previewlanguage": "json"
            }
          ],
          "event": [],
          "protocolProfileBehavior": {
            "disableBodyPruning": true
          }
        }
      ],
      "event": []
    },
    {
      "id": "ecd17826-7c60-4769-99fc-8123032c516f",
      "name": "Cities",
      "description": {
        "content": "",
        "type": "text/plain"
      },
      "item": [
        {
          "id": "0e2ea706-6200-457f-80ea-b1b9d457efc3",
          "name": "List Cities By Country",
          "request": {
            "name": "List Cities By Country",
            "description": {
              "content": "Get all cities for a specific country including their names and slugs.",
              "type": "text/plain"
            },
            "url": {
              "path": [
                "countries",
                ":id",
                "cities"
              ],
              "host": [
                "{{baseUrl}}"
              ],
              "query": [],
              "variable": [
                {
                  "disabled": false,
                  "type": "any",
                  "value": "<string>",
                  "key": "id",
                  "description": "(Required) Country slug or alpha-2 code"
                }
              ]
            },
            "header": [
              {
                "key": "Accept",
                "value": "application/json"
              }
            ],
            "method": "GET",
            "auth": null
          },
          "response": [
            {
              "id": "59ac64a2-cd50-418c-b741-b8092ff28708",
              "name": "List of cities",
              "originalRequest": {
                "url": {
                  "path": [
                    "countries",
                    ":id",
                    "cities"
                  ],
                  "host": [
                    "{{baseUrl}}"
                  ],
                  "query": [],
                  "variable": [
                    {
                      "disabled": false,
                      "type": "any",
                      "value": "<string>",
                      "key": "id",
                      "description": "(Required) Country slug or alpha-2 code"
                    }
                  ]
                },
                "header": [
                  {
                    "description": {
                      "content": "Added as a part of security scheme: apikey",
                      "type": "text/plain"
                    },
                    "key": "X-API-Key",
                    "value": "<API Key>"
                  },
                  {
                    "key": "Accept",
                    "value": "application/json"
                  }
                ],
                "method": "GET",
                "body": {}
              },
              "status": "OK",
              "code": 200,
              "header": [
                {
                  "key": "Content-Type",
                  "value": "application/json"
                }
              ],
              "body": "{\n  \"cities\": [\n    {\n      \"name\": \"string\",\n      \"slug\": \"string\",\n      \"country\": \"string\"\n    },\n    {\n      \"name\": \"string\",\n      \"slug\": \"string\",\n      \"country\": \"string\"\n    }\n  ],\n  \"count\": 8720\n}",
              "cookie": [],
              "_postman_previewlanguage": "json"
            },
            {
              "id": "615e77b2-d618-4593-ad5e-90c1d21ea7ea",
              "name": "Resource not found",
              "originalRequest": {
                "url": {
                  "path": [
                    "countries",
                    ":id",
                    "cities"
                  ],
                  "host": [
                    "{{baseUrl}}"
                  ],
                  "query": [],
                  "variable": [
                    {
                      "disabled": false,
                      "type": "any",
                      "value": "<string>",
                      "key": "id",
                      "description": "(Required) Country slug or alpha-2 code"
                    }
                  ]
                },
                "header": [
                  {
                    "description": {
                      "content": "Added as a part of security scheme: apikey",
                      "type": "text/plain"
                    },
                    "key": "X-API-Key",
                    "value": "<API Key>"
                  },
                  {
                    "key": "Accept",
                    "value": "application/json"
                  }
                ],
                "method": "GET",
                "body": {}
              },
              "status": "Not Found",
              "code": 404,
              "header": [
                {
                  "key": "Content-Type",
                  "value": "application/json"
                }
              ],
              "body": "{\n  \"error\": \"string\",\n  \"message\": \"string\",\n  \"statusCode\": 9675\n}",
              "cookie": [],
              "_postman_previewlanguage": "json"
            }
          ],
          "event": [],
          "protocolProfileBehavior": {
            "disableBodyPruning": true
          }
        },
        {
          "id": "927f468c-6549-4237-95a5-004a915d1830",
          "name": "Get City",
          "request": {
            "name": "Get City",
            "description": {
              "content": "Get detailed information for a specific city by slug.",
              "type": "text/plain"
            },
            "url": {
              "path": [
                "cities",
                ":id"
              ],
              "host": [
                "{{baseUrl}}"
              ],
              "query": [],
              "variable": [
                {
                  "disabled": false,
                  "type": "any",
                  "value": "<string>",
                  "key": "id",
                  "description": "(Required) City slug"
                }
              ]
            },
            "header": [
              {
                "key": "Accept",
                "value": "application/json"
              }
            ],
            "method": "GET",
            "auth": null
          },
          "response": [
            {
              "id": "e84ab679-6f26-4278-8351-fe17e98b14a6",
              "name": "City details",
              "originalRequest": {
                "url": {
                  "path": [
                    "cities",
                    ":id"
                  ],
                  "host": [
                    "{{baseUrl}}"
                  ],
                  "query": [],
                  "variable": [
                    {
                      "disabled": false,
                      "type": "any",
                      "value": "<string>",
                      "key": "id",
                      "description": "(Required) City slug"
                    }
                  ]
                },
                "header": [
                  {
                    "description": {
                      "content": "Added as a part of security scheme: apikey",
                      "type": "text/plain"
                    },
                    "key": "X-API-Key",
                    "value": "<API Key>"
                  },
                  {
                    "key": "Accept",
                    "value": "application/json"
                  }
                ],
                "method": "GET",
                "body": {}
              },
              "status": "OK",
              "code": 200,
              "header": [
                {
                  "key": "Content-Type",
                  "value": "application/json"
                }
              ],
              "body": "{\n  \"name\": \"string\",\n  \"slug\": \"string\",\n  \"country\": \"string\",\n  \"population\": 2374,\n  \"timezone\": \"string\",\n  \"latitude\": 5763.8742522392395,\n  \"longitude\": 8911.2218726617\n}",
              "cookie": [],
              "_postman_previewlanguage": "json"
            },
            {
              "id": "109a3b2d-161c-4a15-9a77-54d98266785b",
              "name": "Resource not found",
              "originalRequest": {
                "url": {
                  "path": [
                    "cities",
                    ":id"
                  ],
                  "host": [
                    "{{baseUrl}}"
                  ],
                  "query": [],
                  "variable": [
                    {
                      "disabled": false,
                      "type": "any",
                      "value": "<string>",
                      "key": "id",
                      "description": "(Required) City slug"
                    }
                  ]
                },
                "header": [
                  {
                    "description": {
                      "content": "Added as a part of security scheme: apikey",
                      "type": "text/plain"
                    },
                    "key": "X-API-Key",
                    "value": "<API Key>"
                  },
                  {
                    "key": "Accept",
                    "value": "application/json"
                  }
                ],
                "method": "GET",
                "body": {}
              },
              "status": "Not Found",
              "code": 404,
              "header": [
                {
                  "key": "Content-Type",
                  "value": "application/json"
                }
              ],
              "body": "{\n  \"error\": \"string\",\n  \"message\": \"string\",\n  \"statusCode\": 9675\n}",
              "cookie": [],
              "_postman_previewlanguage": "json"
            }
          ],
          "event": [],
          "protocolProfileBehavior": {
            "disableBodyPruning": true
          }
        }
      ],
      "event": []
    },
    {
      "id": "87e81a90-c3d9-4b56-bf27-ec9d85015b43",
      "name": "Phrases",
      "description": {
        "content": "",
        "type": "text/plain"
      },
      "item": [
        {
          "id": "2206c7c1-250d-4da5-9f0f-5a7fb844de8c",
          "name": "List Phrases By Country",
          "request": {
            "name": "List Phrases By Country",
            "description": {
              "content": "Get travel phrases for the primary language of a country.",
              "type": "text/plain"
            },
            "url": {
              "path": [
                "countries",
                ":id",
                "phrases"
              ],
              "host": [
                "{{baseUrl}}"
              ],
              "query": [
                {
                  "disabled": false,
                  "key": "language",
                  "value": "en",
                  "description": "Source language for translations (en, fr, de, it, es)"
                }
              ],
              "variable": [
                {
                  "disabled": false,
                  "type": "any",
                  "value": "<string>",
                  "key": "id",
                  "description": "(Required) Country slug or alpha-2 code"
                }
              ]
            },
            "header": [
              {
                "key": "Accept",
                "value": "application/json"
              }
            ],
            "method": "GET",
            "auth": null
          },
          "response": [
            {
              "id": "53ae22f4-6fb5-4068-b5f7-f471d3e69ac3",
              "name": "Travel phrases",
              "originalRequest": {
                "url": {
                  "path": [
                    "countries",
                    ":id",
                    "phrases"
                  ],
                  "host": [
                    "{{baseUrl}}"
                  ],
                  "query": [
                    {
                      "key": "language",
                      "value": "en"
                    }
                  ],
                  "variable": [
                    {
                      "disabled": false,
                      "type": "any",
                      "value": "<string>",
                      "key": "id",
                      "description": "(Required) Country slug or alpha-2 code"
                    }
                  ]
                },
                "header": [
                  {
                    "description": {
                      "content": "Added as a part of security scheme: apikey",
                      "type": "text/plain"
                    },
                    "key": "X-API-Key",
                    "value": "<API Key>"
                  },
                  {
                    "key": "Accept",
                    "value": "application/json"
                  }
                ],
                "method": "GET",
                "body": {}
              },
              "status": "OK",
              "code": 200,
              "header": [
                {
                  "key": "Content-Type",
                  "value": "application/json"
                }
              ],
              "body": "{\n  \"language\": \"string\",\n  \"phrases\": [\n    {\n      \"category\": \"string\",\n      \"original\": \"string\",\n      \"translation\": \"string\",\n      \"phonetic\": \"string\"\n    },\n    {\n      \"category\": \"string\",\n      \"original\": \"string\",\n      \"translation\": \"string\",\n      \"phonetic\": \"string\"\n    }\n  ]\n}",
              "cookie": [],
              "_postman_previewlanguage": "json"
            },
            {
              "id": "2ce4a524-5ffd-4cbb-a121-7f80f9f40187",
              "name": "Resource not found",
              "originalRequest": {
                "url": {
                  "path": [
                    "countries",
                    ":id",
                    "phrases"
                  ],
                  "host": [
                    "{{baseUrl}}"
                  ],
                  "query": [
                    {
                      "key": "language",
                      "value": "en"
                    }
                  ],
                  "variable": [
                    {
                      "disabled": false,
                      "type": "any",
                      "value": "<string>",
                      "key": "id",
                      "description": "(Required) Country slug or alpha-2 code"
                    }
                  ]
                },
                "header": [
                  {
                    "description": {
                      "content": "Added as a part of security scheme: apikey",
                      "type": "text/plain"
                    },
                    "key": "X-API-Key",
                    "value": "<API Key>"
                  },
                  {
                    "key": "Accept",
                    "value": "application/json"
                  }
                ],
                "method": "GET",
                "body": {}
              },
              "status": "Not Found",
              "code": 404,
              "header": [
                {
                  "key": "Content-Type",
                  "value": "application/json"
                }
              ],
              "body": "{\n  \"error\": \"string\",\n  \"message\": \"string\",\n  \"statusCode\": 9675\n}",
              "cookie": [],
              "_postman_previewlanguage": "json"
            }
          ],
          "event": [],
          "protocolProfileBehavior": {
            "disableBodyPruning": true
          }
        }
      ],
      "event": []
    },
    {
      "id": "13890764-b315-4725-8da7-2bf225a96f1a",
      "name": "Safety",
      "description": {
        "content": "",
        "type": "text/plain"
      },
      "item": [
        {
          "id": "6aa70ac0-74bd-4e98-af0a-c6818813bb20",
          "name": "Get Country Safety",
          "request": {
            "name": "Get Country Safety",
            "description": {
              "content": "Get safety ratings and travel advisories for a country.",
              "type": "text/plain"
            },
            "url": {
              "path": [
                "countries",
                ":id",
                "safety"
              ],
              "host": [
                "{{baseUrl}}"
              ],
              "query": [],
              "variable": [
                {
                  "disabled": false,
                  "type": "any",
                  "value": "<string>",
                  "key": "id",
                  "description": "(Required) Country slug or alpha-2 code"
                }
              ]
            },
            "header": [
              {
                "key": "Accept",
                "value": "application/json"
              }
            ],
            "method": "GET",
            "auth": null
          },
          "response": [
            {
              "id": "4f803a6d-2685-4795-a0fa-cad6b0e7b519",
              "name": "Safety information",
              "originalRequest": {
                "url": {
                  "path": [
                    "countries",
                    ":id",
                    "safety"
                  ],
                  "host": [
                    "{{baseUrl}}"
                  ],
                  "query": [],
                  "variable": [
                    {
                      "disabled": false,
                      "type": "any",
                      "value": "<string>",
                      "key": "id",
                      "description": "(Required) Country slug or alpha-2 code"
                    }
                  ]
                },
                "header": [
                  {
                    "description": {
                      "content": "Added as a part of security scheme: apikey",
                      "type": "text/plain"
                    },
                    "key": "X-API-Key",
                    "value": "<API Key>"
                  },
                  {
                    "key": "Accept",
                    "value": "application/json"
                  }
                ],
                "method": "GET",
                "body": {}
              },
              "status": "OK",
              "code": 200,
              "header": [
                {
                  "key": "Content-Type",
                  "value": "application/json"
                }
              ],
              "body": "{\n  \"country\": \"string\",\n  \"overallRating\": \"Risky\",\n  \"advisoryLevel\": 3,\n  \"categories\": {\n    \"crime\": \"string\",\n    \"terrorism\": \"string\",\n    \"naturalDisasters\": \"string\"\n  },\n  \"notes\": \"string\"\n}",
              "cookie": [],
              "_postman_previewlanguage": "json"
            },
            {
              "id": "ab54940d-adcd-446b-b285-6cd883b25668",
              "name": "Resource not found",
              "originalRequest": {
                "url": {
                  "path": [
                    "countries",
                    ":id",
                    "safety"
                  ],
                  "host": [
                    "{{baseUrl}}"
                  ],
                  "query": [],
                  "variable": [
                    {
                      "disabled": false,
                      "type": "any",
                      "value": "<string>",
                      "key": "id",
                      "description": "(Required) Country slug or alpha-2 code"
                    }
                  ]
                },
                "header": [
                  {
                    "description": {
                      "content": "Added as a part of security scheme: apikey",
                      "type": "text/plain"
                    },
                    "key": "X-API-Key",
                    "value": "<API Key>"
                  },
                  {
                    "key": "Accept",
                    "value": "application/json"
                  }
                ],
                "method": "GET",
                "body": {}
              },
              "status": "Not Found",
              "code": 404,
              "header": [
                {
                  "key": "Content-Type",
                  "value": "application/json"
                }
              ],
              "body": "{\n  \"error\": \"string\",\n  \"message\": \"string\",\n  \"statusCode\": 9675\n}",
              "cookie": [],
              "_postman_previewlanguage": "json"
            }
          ],
          "event": [],
          "protocolProfileBehavior": {
            "disableBodyPruning": true
          }
        }
      ],
      "event": []
    },
    {
      "id": "7be3e26d-72f6-40ca-9f8b-f8b3d83d808f",
      "name": "Cost",
      "description": {
        "content": "",
        "type": "text/plain"
      },
      "item": [
        {
          "id": "84c10570-9707-4010-a307-5c9d0f29b433",
          "name": "Get Country Cost",
          "request": {
            "name": "Get Country Cost",
            "description": {
              "content": "Get cost of living and travel budget estimates for a country.",
              "type": "text/plain"
            },
            "url": {
              "path": [
                "countries",
                ":id",
                "cost"
              ],
              "host": [
                "{{baseUrl}}"
              ],
              "query": [],
              "variable": [
                {
                  "disabled": false,
                  "type": "any",
                  "value": "<string>",
                  "key": "id",
                  "description": "(Required) Country slug or alpha-2 code"
                }
              ]
            },
            "header": [
              {
                "key": "Accept",
                "value": "application/json"
              }
            ],
            "method": "GET",
            "auth": null
          },
          "response": [
            {
              "id": "57455c16-4b50-4ef1-b168-c39012527d5a",
              "name": "Cost information",
              "originalRequest": {
                "url": {
                  "path": [
                    "countries",
                    ":id",
                    "cost"
                  ],
                  "host": [
                    "{{baseUrl}}"
                  ],
                  "query": [],
                  "variable": [
                    {
                      "disabled": false,
                      "type": "any",
                      "value": "<string>",
                      "key": "id",
                      "description": "(Required) Country slug or alpha-2 code"
                    }
                  ]
                },
                "header": [
                  {
                    "description": {
                      "content": "Added as a part of security scheme: apikey",
                      "type": "text/plain"
                    },
                    "key": "X-API-Key",
                    "value": "<API Key>"
                  },
                  {
                    "key": "Accept",
                    "value": "application/json"
                  }
                ],
                "method": "GET",
                "body": {}
              },
              "status": "OK",
              "code": 200,
              "header": [
                {
                  "key": "Content-Type",
                  "value": "application/json"
                }
              ],
              "body": "{\n  \"country\": \"string\",\n  \"currency\": \"string\",\n  \"budgetPerDay\": 2382.895962615176,\n  \"midRangePerDay\": 1007.8134109194092,\n  \"luxuryPerDay\": 9023.159824118778,\n  \"categories\": {\n    \"accommodation\": 9202.830318567718,\n    \"food\": 6200.401891400595,\n    \"transport\": 6302.62481847722\n  }\n}",
              "cookie": [],
              "_postman_previewlanguage": "json"
            },
            {
              "id": "859cda0c-99f1-4c30-b184-dfe20dc264b1",
              "name": "Resource not found",
              "originalRequest": {
                "url": {
                  "path": [
                    "countries",
                    ":id",
                    "cost"
                  ],
                  "host": [
                    "{{baseUrl}}"
                  ],
                  "query": [],
                  "variable": [
                    {
                      "disabled": false,
                      "type": "any",
                      "value": "<string>",
                      "key": "id",
                      "description": "(Required) Country slug or alpha-2 code"
                    }
                  ]
                },
                "header": [
                  {
                    "description": {
                      "content": "Added as a part of security scheme: apikey",
                      "type": "text/plain"
                    },
                    "key": "X-API-Key",
                    "value": "<API Key>"
                  },
                  {
                    "key": "Accept",
                    "value": "application/json"
                  }
                ],
                "method": "GET",
                "body": {}
              },
              "status": "Not Found",
              "code": 404,
              "header": [
                {
                  "key": "Content-Type",
                  "value": "application/json"
                }
              ],
              "body": "{\n  \"error\": \"string\",\n  \"message\": \"string\",\n  \"statusCode\": 9675\n}",
              "cookie": [],
              "_postman_previewlanguage": "json"
            }
          ],
          "event": [],
          "protocolProfileBehavior": {
            "disableBodyPruning": true
          }
        }
      ],
      "event": []
    },
    {
      "id": "a24239cb-cd27-43c2-a4ea-8305d3e23a84",
      "name": "Visa",
      "description": {
        "content": "",
        "type": "text/plain"
      },
      "item": [
        {
          "id": "15709fb2-87a0-4bbc-b19a-712c4e81ff48",
          "name": "Get Visa Requirements",
          "request": {
            "name": "Get Visa Requirements",
            "description": {
              "content": "Get visa requirements for a destination country based on passport country.",
              "type": "text/plain"
            },
            "url": {
              "path": [
                "countries",
                ":id",
                "visa"
              ],
              "host": [
                "{{baseUrl}}"
              ],
              "query": [
                {
                  "disabled": false,
                  "key": "passport",
                  "value": "<string>",
                  "description": "(Required) Passport country alpha-2 code"
                }
              ],
              "variable": [
                {
                  "disabled": false,
                  "type": "any",
                  "value": "<string>",
                  "key": "id",
                  "description": "(Required) Destination country slug or alpha-2 code"
                }
              ]
            },
            "header": [
              {
                "key": "Accept",
                "value": "application/json"
              }
            ],
            "method": "GET",
            "auth": null
          },
          "response": [
            {
              "id": "4f9d2d96-7164-4f9e-8ce1-646cbc49f175",
              "name": "Visa requirements",
              "originalRequest": {
                "url": {
                  "path": [
                    "countries",
                    ":id",
                    "visa"
                  ],
                  "host": [
                    "{{baseUrl}}"
                  ],
                  "query": [
                    {
                      "key": "passport",
                      "value": "<string>"
                    }
                  ],
                  "variable": [
                    {
                      "disabled": false,
                      "type": "any",
                      "value": "<string>",
                      "key": "id",
                      "description": "(Required) Destination country slug or alpha-2 code"
                    }
                  ]
                },
                "header": [
                  {
                    "description": {
                      "content": "Added as a part of security scheme: apikey",
                      "type": "text/plain"
                    },
                    "key": "X-API-Key",
                    "value": "<API Key>"
                  },
                  {
                    "key": "Accept",
                    "value": "application/json"
                  }
                ],
                "method": "GET",
                "body": {}
              },
              "status": "OK",
              "code": 200,
              "header": [
                {
                  "key": "Content-Type",
                  "value": "application/json"
                }
              ],
              "body": "{\n  \"destination\": \"string\",\n  \"passport\": \"string\",\n  \"requirement\": \"Visa on Arrival\",\n  \"maxStay\": 5539,\n  \"notes\": \"string\"\n}",
              "cookie": [],
              "_postman_previewlanguage": "json"
            },
            {
              "id": "106d8c1f-246f-4b62-a9a3-0aa4d51c25bb",
              "name": "Resource not found",
              "originalRequest": {
                "url": {
                  "path": [
                    "countries",
                    ":id",
                    "visa"
                  ],
                  "host": [
                    "{{baseUrl}}"
                  ],
                  "query": [
                    {
                      "key": "passport",
                      "value": "<string>"
                    }
                  ],
                  "variable": [
                    {
                      "disabled": false,
                      "type": "any",
                      "value": "<string>",
                      "key": "id",
                      "description": "(Required) Destination country slug or alpha-2 code"
                    }
                  ]
                },
                "header": [
                  {
                    "description": {
                      "content": "Added as a part of security scheme: apikey",
                      "type": "text/plain"
                    },
                    "key": "X-API-Key",
                    "value": "<API Key>"
                  },
                  {
                    "key": "Accept",
                    "value": "application/json"
                  }
                ],
                "method": "GET",
                "body": {}
              },
              "status": "Not Found",
              "code": 404,
              "header": [
                {
                  "key": "Content-Type",
                  "value": "application/json"
                }
              ],
              "body": "{\n  \"error\": \"string\",\n  \"message\": \"string\",\n  \"statusCode\": 9675\n}",
              "cookie": [],
              "_postman_previewlanguage": "json"
            }
          ],
          "event": [],
          "protocolProfileBehavior": {
            "disableBodyPruning": true
          }
        }
      ],
      "event": []
    },
    {
      "id": "ed9bc4d6-aade-4c0c-a547-d8c93961e374",
      "name": "Health",
      "description": {
        "content": "",
        "type": "text/plain"
      },
      "item": [
        {
          "id": "280b1780-ac57-4eb7-a13e-af049a9761eb",
          "name": "Get Country Health",
          "request": {
            "name": "Get Country Health",
            "description": {
              "content": "Get health advisories, vaccination requirements, and medical information for a country.",
              "type": "text/plain"
            },
            "url": {
              "path": [
                "countries",
                ":id",
                "health"
              ],
              "host": [
                "{{baseUrl}}"
              ],
              "query": [],
              "variable": [
                {
                  "disabled": false,
                  "type": "any",
                  "value": "<string>",
                  "key": "id",
                  "description": "(Required) Country slug or alpha-2 code"
                }
              ]
            },
            "header": [
              {
                "key": "Accept",
                "value": "application/json"
              }
            ],
            "method": "GET",
            "auth": null
          },
          "response": [
            {
              "id": "7bc73815-c091-46ce-a67b-dc056b8eac47",
              "name": "Health information",
              "originalRequest": {
                "url": {
                  "path": [
                    "countries",
                    ":id",
                    "health"
                  ],
                  "host": [
                    "{{baseUrl}}"
                  ],
                  "query": [],
                  "variable": [
                    {
                      "disabled": false,
                      "type": "any",
                      "value": "<string>",
                      "key": "id",
                      "description": "(Required) Country slug or alpha-2 code"
                    }
                  ]
                },
                "header": [
                  {
                    "description": {
                      "content": "Added as a part of security scheme: apikey",
                      "type": "text/plain"
                    },
                    "key": "X-API-Key",
                    "value": "<API Key>"
                  },
                  {
                    "key": "Accept",
                    "value": "application/json"
                  }
                ],
                "method": "GET",
                "body": {}
              },
              "status": "OK",
              "code": 200,
              "header": [
                {
                  "key": "Content-Type",
                  "value": "application/json"
                }
              ],
              "body": "{\n  \"country\": \"string\",\n  \"vaccinations\": [\n    {\n      \"name\": \"string\",\n      \"requirement\": \"Required\"\n    },\n    {\n      \"name\": \"string\",\n      \"requirement\": \"Recommended\"\n    }\n  ],\n  \"healthRisks\": [\n    \"string\",\n    \"string\"\n  ],\n  \"drinkingWater\": \"Boil Advisories\",\n  \"medicalFacilities\": \"Limited\"\n}",
              "cookie": [],
              "_postman_previewlanguage": "json"
            },
            {
              "id": "cf62a62a-81fc-4798-b303-70149db4629f",
              "name": "Resource not found",
              "originalRequest": {
                "url": {
                  "path": [
                    "countries",
                    ":id",
                    "health"
                  ],
                  "host": [
                    "{{baseUrl}}"
                  ],
                  "query": [],
                  "variable": [
                    {
                      "disabled": false,
                      "type": "any",
                      "value": "<string>",
                      "key": "id",
                      "description": "(Required) Country slug or alpha-2 code"
                    }
                  ]
                },
                "header": [
                  {
                    "description": {
                      "content": "Added as a part of security scheme: apikey",
                      "type": "text/plain"
                    },
                    "key": "X-API-Key",
                    "value": "<API Key>"
                  },
                  {
                    "key": "Accept",
                    "value": "application/json"
                  }
                ],
                "method": "GET",
                "body": {}
              },
              "status": "Not Found",
              "code": 404,
              "header": [
                {
                  "key": "Content-Type",
                  "value": "application/json"
                }
              ],
              "body": "{\n  \"error\": \"string\",\n  \"message\": \"string\",\n  \"statusCode\": 9675\n}",
              "cookie": [],
              "_postman_previewlanguage": "json"
            }
          ],
          "event": [],
          "protocolProfileBehavior": {
            "disableBodyPruning": true
          }
        }
      ],
      "event": []
    }
  ],
  "event": [],
  "variable": [
    {
      "type": "string",
      "value": "https://api.thebasetrip.com/v3",
      "key": "baseUrl"
    }
  ],
  "auth": {
    "type": "apikey",
    "apikey": [
      {
        "key": "key",
        "value": "X-API-Key"
      },
      {
        "key": "value",
        "value": "{{apiKey}}"
      },
      {
        "key": "in",
        "value": "header"
      }
    ]
  },
  "info": {
    "_postman_id": "0e5af5d8-ebaa-4455-80de-20f40030694d",
    "name": "Basetrip API",
    "schema": "https://schema.getpostman.com/json/collection/v2.1.0/collection.json",
    "description": {
      "content": "The Basetrip API provides travel intelligence data including country and city information, travel phrases, safety ratings, visa requirements, cost of living data, and health advisories. Designed to help travel platforms differentiate their products and improve traveler experiences.\n\nContact Support:\n Name: Basetrip Support",
      "type": "text/plain"
    }
  }
}